{
  "model": {
    "n_layer": 24,
    "n_head": 16,
    "n_embd": 1280,
    "block_size": 1024,
    "dropout": 0.0,
    "bias": true,
    "vocab_size": 50257,
    "use_gradient_checkpointing": false
  },
  "deepspeed": {
    "train_batch_size": 32,
    "train_micro_batch_size_per_gpu": 4,
    "gradient_accumulation_steps": 8,
    "gradient_clipping": 1.0,
    "fp16": {
      "enabled": true,
      "loss_scale": 0,
      "initial_scale_power": 16,
      "loss_scale_window": 1000,
      "hysteresis": 2,
      "min_loss_scale": 1
    },
    "zero_optimization": {
      "stage": 2,
      "offload_optimizer": {
        "device": "cpu",
        "pin_memory": true
      },
      "contiguous_gradients": true,
      "overlap_comm": true,
      "reduce_scatter": true,
      "reduce_bucket_size": 500000000.0,
      "allgather_bucket_size": 500000000.0
    },
    "optimizer": {
      "type": "Adam",
      "params": {
        "lr": 0.0003,
        "betas": [
          0.9,
          0.95
        ],
        "eps": 1e-08,
        "weight_decay": 0.1
      }
    },
    "scheduler": {
      "type": "WarmupCosineLR",
      "params": {
        "warmup_min_ratio": 0.0,
        "warmup_num_steps": 500,
        "total_num_steps": 50000,
        "cos_min_ratio": 0.1
      }
    },
    "activation_checkpointing": {
      "partition_activations": false,
      "contiguous_memory_optimization": false,
      "cpu_checkpointing": false
    }
  },
  "training": {
    "size_name": "500M",
    "cpu_offload": true,
    "gradient_checkpointing": false,
    "batch_size": 4,
    "grad_accum": 8,
    "lr": 0.0003,
    "warmup_steps": 500,
    "max_steps": 50000,
    "block_size": 1024
  },
  "benchmark_results": {
    "peak_gpu_gb": 6.37,
    "tokens_per_sec": 1627,
    "cpu_ram_gb": 30.3,
    "vram_utilization": 0.53
  },
  "generated_by": "benchmark/readiness_gate.py",
  "generated_at": "2026-02-24T12:58:25+00:00",
  "reviewed_at": "2026-02-24T21:00:00+00:00"
}
